{"pretrained_model_name": "spy24/autonlp-paraphrasing-607217177", "description": "---\ntags: autonlp\nlanguage: unk\nwidget:\n- text: \"I love AutoNLP \ud83e\udd17\"\ndatasets:\n- spy24/autonlp-data-paraphrasing\nco2_eq_emissions: 193.70003779879124\n---\n\n# Model Trained Using AutoNLP\n\n- Problem type: Summarization\n- Model ID: 607217177\n- CO2 Emissions (in grams): 193.70003779879124\n\n## Validation Metrics\n\n- Loss: 1.2881609201431274\n- Rouge1: 48.3375\n- Rouge2: 25.9756\n- RougeL: 42.2748\n- RougeLsum: 42.2797\n- Gen Len: 18.4359\n\n## Usage\n\nYou can use cURL to access this model:\n\n```\n$ curl -X POST -H \"Authorization: Bearer YOUR_HUGGINGFACE_API_KEY\" -H \"Content-Type: application/json\" -d '{\"inputs\": \"I love AutoNLP\"}' https://api-inference.huggingface.co/spy24/autonlp-paraphrasing-607217177\n```", "size_bytes": "891730879", "downloads": 6}