{"pretrained_model_name": "LeoCordoba/beto2beto-mlsum", "description": "---\nlanguage: es\ntags:\n- summarization\n- spanish\n- encoder-decoder\n- beto\nlicense: apache-2.0\ndatasets:\n- mlsum - es\nmodel-index:\n- name: beto2beto-mlsum\n  results:\n  - task: \n      type: summarization  # Required. Example: automatic-speech-recognition\n      name: abstractive summarization  # Optional. Example: Speech Recognition\n    dataset:\n      type: mlsum  # Required. Example: common_voice. Use dataset id from https://hf.co/datasets\n      name: mlsum-es  # Required. Example: Common Voice zh-CN\n      args: es         # Optional. Example: zh-CN\n    metrics:\n       - name: rouge1\n         type: rouge1\n         value: 25.8639\n       - name: rouge2\n         type: rouge2\n         value: 8.911\n       - name: rougeL\n         type: rougeL\n         value: 21.2426\n       - name: rougeLsum\n         type: rougeLsum\n         value: 21.5859\nwidget:\n- text: | \n    La chocotorta, el tradicional y pr\u00e1ctico antojo dulce de los argentinos, fue elegida como el mejor postre del mundo por cr\u00edticos de restaurants internacionales, a casi 40 a\u00f1os de su creaci\u00f3n. El r\u00e1nking Taste Atlas ubic\u00f3 primero en su lista al postre insignia local de galletitas, queso crema y dulce de leche, por delante del helado de pistacho italiano y la tarta alemana de manzana. \u201cEste postre argentino sin hornear fue influenciado por la cocina italiana y se inspir\u00f3 en el famoso tiramis\u00fa italiano. Est\u00e1 elaborado con tres ingredientes b\u00e1sicos argentinos: galletas de chocolate, dulce de leche y queso crema\u201d, explica la p\u00e1gina web que exhorta a los turistas de todo el mundo a que prueben la chocotorta. En la votaci\u00f3n, super\u00f3 tambi\u00e9n a los waffles belgas y el zserb\u00f3 h\u00fangaro. A nivel local le sigue el alfajor, con 4,2 puntos contra los 4,7 de la torta. En el texto que acompa\u00f1a al list\u00f3n dorado de \u201cpostre n\u00famero uno\", los expertos ense\u00f1an adem\u00e1s c\u00f3mo se hacen las chocotortas, paso por paso. \u201cLas galletas se ablandan en leche y se cubren con una combinaci\u00f3n de queso crema y dulce de leche. Las formas de la chocotorta pueden variar, mientras que las galletas se pueden remojar con leche con chocolate, caf\u00e9 o incluso licor de caf\u00e9\u201d, detallan. Por \u00faltimo, adjudican su creaci\u00f3n a una \u201ccampa\u00f1a de m\u00e1rketing\u201d dise\u00f1ada para promover las galletitas ic\u00f3nicas que le dan su nombre. La chocotorta, infaltable en los cumplea\u00f1os argentinos, fue creada en 1982 por una creativa de las agencias m\u00e1s importantes del pa\u00eds, Marit\u00e9 Mabraga\u00f1a.\n\n---\n## beto2beto-mlsum\nThis model was trained on the Spanish section of MLSum: https://paperswithcode.com/sota/abstractive-text-summarization-on-mlsum.\n\n## Hyperparameters\n    {\n    \"dataset_config\": \"es\",\n    \"dataset_name\": \"mlsum\",\n    \"do_eval\": true,\n    \"do_predict\": true,\n    \"do_train\": true,\n    \"fp16\": true,\n    \"max_target_length\": 64,\n    \"num_train_epochs\": 10,\n    \"per_device_eval_batch_size\": 4,\n    \"per_device_train_batch_size\": 4,\n    \"predict_with_generate\": true,\n    \"sagemaker_container_log_level\": 20,\n    \"sagemaker_program\": \"run_summarization.py\",\n    \"seed\": 7,\n    \"summary_column\": \"summary\",\n    \"text_column\": \"text\"\n}\n## Usage\n## Results\n| metric | score |\n| --- | ----- |\n| validation_loss | 2.5021677017211914 |\n| validation_rouge1 | 26.1256 |\n| validation_rouge2 | 9.2552 |\n| validation_rougeL | 21.4899 |\n| validation_rougeLsum | 21.8194 |\n| test_loss | 2.57672381401062 |\n| test_rouge1 | 25.8639 |\n| test_rouge2 | 8.911 |\n| test_rougeL | 21.2426 |\n| test_rougeLsum | 21.5859 |\n", "size_bytes": "992553531", "downloads": 31}