{"pretrained_model_name": "YtBig/href-v1", "description": "---\ntags:\n- autotrain\n- summarization\nlanguage:\n- en\nwidget:\n- text: \"I love AutoTrain \ud83e\udd17\"\nco2_eq_emissions:\n  emissions: 2.970316260186869\n---\n\n# Model Trained Using AutoTrain\n\n- Problem type: Summarization\n- Model ID: 1900964639\n- CO2 Emissions (in grams): 2.9703\n\n## Validation Metrics\n\n- Loss: 2.262\n- Rouge1: 27.046\n- Rouge2: 14.251\n- RougeL: 24.913\n- RougeLsum: 25.284\n- Gen Len: 19.888\n\n## Usage\n\nYou can use cURL to access this model:\n\n```\n$ curl -X POST -H \"Authorization: Bearer YOUR_HUGGINGFACE_API_KEY\" -H \"Content-Type: application/json\" -d '{\"inputs\": \"I love AutoTrain\"}' https://api-inference.huggingface.co/aalbertini90/autotrain-href-1900964639\n```", "size_bytes": "1625537793", "downloads": 8}